clprint.py
core/__init__.py
core/decorator.py
clprint-0.0.10.dist-info/LICENSE
clprint-0.0.10.dist-info/METADATA
clprint-0.0.10.dist-info/WHEEL
clprint-0.0.10.dist-info/top_level.txt
clprint-0.0.10.dist-info/RECORD
