Metadata-Version: 2.1
Name: clprint
Version: 0.0.10
Summary: A package to print colored text in terminal
Author-email: Latheesh V M <latheeshvmv@gmail.com>
Project-URL: Homepage, https://github.com/latheeshvm/clprint
Project-URL: Bug Tracker, https://github.com/latheeshvm/clprint/issues
Keywords: color,print,terminal,clprint,colorprint,color-print
Classifier: Programming Language :: Python :: 3
Classifier: License :: OSI Approved :: MIT License
Classifier: Operating System :: OS Independent
Requires-Python: >=3.7
License-File: LICENSE
